{
  "value": {
    "numberPending": 0,
    "completeListFlag": false,
    "movements": [{
      "movementText": "TERUGBETALING WOONKREDIET                ",
      "sequenceNb": "0257",
      "pending": false,
      "period": "YESTERDAY",
      "annexes": [],
      "otherParty": "TERUGBETALING WOONKREDIET       ",
      "operationId": "BE46235022516136#EUR#75#0257##1",
      "executionDate": "20190801",
      "amount": "-437,22",
      "currency": "EUR",
      "description1": "009-7829087-28\\r\\nBANKREFERENTIE : 1908010446585471",
      "description2": "VALUTADATUM : 01/08/2019",
      "valueDate": "20190801",
      "detailPresent": false
    }, {
      "movementText": "EUROPESE OVERSCHRIJVING NAAR             ",
      "sequenceNb": "0256",
      "pending": false,
      "period": "PREVIOUS",
      "annexes": [],
      "otherParty": "BE42001513418854",
      "operationId": "BE46235022516136#EUR#75#0256##2",
      "executionDate": "20190730",
      "amount": "-10,00",
      "currency": "EUR",
      "description1": "015-0018280-20\\r\\nBE42001513418854",
      "description2": "BIC GEBABEBB    VIA MOBILE BANKING\\r\\nZONDER MEDEDELING\\r\\nBANKREFERENTIE : 1907301538210960\\r\\nVALUTADATUM : 30/07/2019",
      "valueDate": "20190730",
      "detailPresent": false
    }, {
      "movementText": "EUROPESE OVERSCHRIJVING NAAR             ",
      "sequenceNb": "0255",
      "pending": false,
      "period": "PREVIOUS",
      "annexes": [],
      "otherParty": "BE91001814353876",
      "operationId": "BE46235022516136#EUR#75#0255##3",
      "executionDate": "20190730",
      "amount": "-35,00",
      "currency": "EUR",
      "description1": "3120360P\\r\\nBE91001814353876",
      "description2": "BIC GEBABEBB    VIA MOBILE BANKING\\r\\nZONDER MEDEDELING\\r\\nBANKREFERENTIE : 1907301539082138\\r\\nVALUTADATUM : 30/07/2019",
      "valueDate": "20190730",
      "detailPresent": false
    }, {
      "movementText": "EUROPESE OVERSCHRIJVING NAAR             ",
      "sequenceNb": "0254",
      "pending": false,
      "period": "PREVIOUS",
      "annexes": [],
      "otherParty": "BE66001162743343",
      "operationId": "BE46235022516136#EUR#75#0254##4",
      "executionDate": "20190725",
      "amount": "-35,00",
      "currency": "EUR",
      "description1": "SAMBI BOUPHANG\\r\\nBE66001162743343",
      "description2": "BIC GEBABEBB    VIA MOBILE BANKING\\r\\nMEDEDELING :\\r\\nZBJZJZJ\\r\\nBANKREFERENTIE : 1907251458599114\\r\\nVALUTADATUM : 25/07/2019",
      "valueDate": "20190725",
      "detailPresent": false
    }, {
      "movementText": "EUROPESE OVERSCHRIJVING NAAR             ",
      "sequenceNb": "0253",
      "pending": false,
      "period": "PREVIOUS",
      "annexes": [],
      "otherParty": "BE11363094488548",
      "operationId": "BE46235022516136#EUR#75#0253##5",
      "executionDate": "20190710",
      "amount": "-82,00",
      "currency": "EUR",
      "description1": "ABBAA\\r\\nBE11363094488548",
      "description2": "BIC BBRUBEBB    VIA MOBILE BANKING\\r\\nZONDER MEDEDELING\\r\\nBANKREFERENTIE : 1907100939457567\\r\\nVALUTADATUM : 10/07/2019",
      "valueDate": "20190710",
      "detailPresent": false
    }, {
      "movementText": "EUROPESE OVERSCHRIJVING NAAR             ",
      "sequenceNb": "0252",
      "pending": false,
      "period": "PREVIOUS",
      "annexes": [],
      "otherParty": "BE91001814353876",
      "operationId": "BE46235022516136#EUR#75#0252##6",
      "executionDate": "20190709",
      "amount": "-31,00",
      "currency": "EUR",
      "description1": "3120360P\\r\\nBE91001814353876",
      "description2": "BIC GEBABEBB    VIA MOBILE BANKING\\r\\nZONDER MEDEDELING\\r\\nBANKREFERENTIE : 1907091050406242\\r\\nVALUTADATUM : 09/07/2019",
      "valueDate": "20190709",
      "detailPresent": false
    }, {
      "movementText": "EUROPESE OVERSCHRIJVING NAAR             ",
      "sequenceNb": "0251",
      "pending": false,
      "period": "PREVIOUS",
      "annexes": [],
      "otherParty": "BE11363094488548",
      "operationId": "BE46235022516136#EUR#75#0251##7",
      "executionDate": "20190709",
      "amount": "-63,00",
      "currency": "EUR",
      "description1": "ABAA\\r\\nBE11363094488548",
      "description2": "BIC BBRUBEBB    VIA MOBILE BANKING\\r\\nZONDER MEDEDELING\\r\\nBANKREFERENTIE : 1907091238174764\\r\\nVALUTADATUM : 09/07/2019",
      "valueDate": "20190709",
      "detailPresent": false
    }, {
      "movementText": "EUROPESE OVERSCHRIJVING NAAR             ",
      "sequenceNb": "0250",
      "pending": false,
      "period": "PREVIOUS",
      "annexes": [],
      "otherParty": "BE11363094488548",
      "operationId": "BE46235022516136#EUR#75#0250##8",
      "executionDate": "20190709",
      "amount": "-68,00",
      "currency": "EUR",
      "description1": "AAABBB0\\r\\nBE11363094488548",
      "description2": "BIC BBRUBEBB    VIA MOBILE BANKING\\r\\nZONDER MEDEDELING\\r\\nBANKREFERENTIE : 1907091054432522\\r\\nVALUTADATUM : 09/07/2019",
      "valueDate": "20190709",
      "detailPresent": false
    }, {
      "movementText": "EUROPESE OVERSCHRIJVING NAAR             ",
      "sequenceNb": "0249",
      "pending": false,
      "period": "PREVIOUS",
      "annexes": [],
      "otherParty": "BE39001626177819",
      "operationId": "BE46235022516136#EUR#75#0249##9",
      "executionDate": "20190709",
      "amount": "-69,00",
      "currency": "EUR",
      "description1": "VHG SM PVUZ\\r\\nBE39001626177819",
      "description2": "BIC GEBABEBB    VIA MOBILE BANKING\\r\\nZONDER MEDEDELING\\r\\nBANKREFERENTIE : 1907091150451409\\r\\nVALUTADATUM : 09/07/2019",
      "valueDate": "20190709",
      "detailPresent": false
    }, {
      "movementText": "EUROPESE OVERSCHRIJVING NAAR             ",
      "sequenceNb": "0248",
      "pending": false,
      "period": "PREVIOUS",
      "annexes": [],
      "otherParty": "BE91001814353876",
      "operationId": "BE46235022516136#EUR#75#0248##10",
      "executionDate": "20190709",
      "amount": "-76,00",
      "currency": "EUR",
      "description1": "3120360P\\r\\nBE91001814353876",
      "description2": "BIC GEBABEBB    VIA MOBILE BANKING\\r\\nZONDER MEDEDELING\\r\\nBANKREFERENTIE : 1907091237155047\\r\\nVALUTADATUM : 09/07/2019",
      "valueDate": "20190709",
      "detailPresent": false
    }, {
      "movementText": "EUROPESE OVERSCHRIJVING NAAR             ",
      "sequenceNb": "0247",
      "pending": false,
      "period": "PREVIOUS",
      "annexes": [],
      "otherParty": "BE11363094488548",
      "operationId": "BE46235022516136#EUR#75#0247##11",
      "executionDate": "20190709",
      "amount": "-76,00",
      "currency": "EUR",
      "description1": "AAAAB\\r\\nBE11363094488548",
      "description2": "BIC BBRUBEBB    VIA MOBILE BANKING\\r\\nZONDER MEDEDELING\\r\\nBANKREFERENTIE : 1907091149090035\\r\\nVALUTADATUM : 09/07/2019",
      "valueDate": "20190709",
      "detailPresent": false
    }, {
      "movementText": "TERUGBETALING WOONKREDIET                ",
      "sequenceNb": "0246",
      "pending": false,
      "period": "PREVIOUS",
      "annexes": [],
      "otherParty": "TERUGBETALING WOONKREDIET       ",
      "operationId": "BE46235022516136#EUR#75#0246##12",
      "executionDate": "20190701",
      "amount": "-436,80",
      "currency": "EUR",
      "description1": "009-7829087-28\\r\\nBANKREFERENTIE : 1907010519378456",
      "description2": "VALUTADATUM : 01/07/2019",
      "valueDate": "20190701",
      "detailPresent": false
    }, {
      "movementText": "BETALING MET BANKKAART                   ",
      "sequenceNb": "0245",
      "pending": false,
      "period": "PREVIOUS",
      "annexes": [],
      "otherParty": "BETALING MET BANKKAART          ",
      "operationId": "BE46235022516136#EUR#75#0245##13",
      "executionDate": "20190615",
      "amount": "-45,79",
      "currency": "EUR",
      "description1": "MET KAART 6703 23XX XXXX X250 1\\r\\nJANSSEN-CLAES  N  HASSELT",
      "description2": "15/06/2019\\r\\nVALUTADATUM : 15/06/2019",
      "valueDate": "20190615",
      "detailPresent": false
    }, {
      "movementText": "BETALING MET BANKKAART                   ",
      "sequenceNb": "0244",
      "pending": false,
      "period": "PREVIOUS",
      "annexes": [],
      "otherParty": "BETALING MET BANKKAART          ",
      "operationId": "BE46235022516136#EUR#75#0244##14",
      "executionDate": "20190614",
      "amount": "-143,93",
      "currency": "EUR",
      "description1": "MET KAART 6703 23XX XXXX X250 1\\r\\nJANSSEN-CLAES  N  HASSELT",
      "description2": "14/06/2019\\r\\nVALUTADATUM : 14/06/2019",
      "valueDate": "20190614",
      "detailPresent": false
    }, {
      "movementText": "EUROPESE OVERSCHRIJVING VAN              ",
      "sequenceNb": "0243",
      "pending": false,
      "period": "PREVIOUS",
      "annexes": [],
      "otherParty": "BE44068893856845",
      "operationId": "BE46235022516136#EUR#75#0243##15",
      "executionDate": "20190614",
      "amount": "5,34",
      "currency": "EUR",
      "description1": "COSTAGOMESXYZ CM-\\r\\nBILLIESXYZ METZELLERXYZ",
      "description2": "1030  KONTZENXYZ\\r\\nBE44 0688 9385 6845  BIC GKCCBEBB\\r\\nREFERTE OPDRACHTGEVER :\\r\\n21168416\\r\\nMEDEDELING :\\r\\n1930738631 - KWARTAAL UITBETALING REM\\r\\nGELDEN CM-MEDIKO PLAN - VANSTRAELEN -",
      "valueDate": "20190614",
      "detailPresent": false
    }, {
      "movementText": "EUROPESE OVERSCHRIJVING VAN              ",
      "sequenceNb": "0242",
      "pending": false,
      "period": "PREVIOUS",
      "annexes": [],
      "otherParty": "BE44068893856845",
      "operationId": "BE46235022516136#EUR#75#0242##16",
      "executionDate": "20190614",
      "amount": "11,75",
      "currency": "EUR",
      "description1": "COSTAGOMESXYZ CM-\\r\\nBILLIESXYZ METZELLERXYZ",
      "description2": "1030  KONTZENXYZ\\r\\nBE44 0688 9385 6845  BIC GKCCBEBB\\r\\nREFERTE OPDRACHTGEVER :\\r\\n21160193\\r\\nMEDEDELING :\\r\\n1930549072 - KWARTAAL UITBETALING REM\\r\\nGELDEN CM-MEDIKO PLAN - DEBRUYNE - AN",
      "valueDate": "20190614",
      "detailPresent": false
    }, {
      "movementText": "EUROPESE OVERSCHRIJVING VAN              ",
      "sequenceNb": "0241",
      "pending": false,
      "period": "PREVIOUS",
      "annexes": [],
      "otherParty": "BE44068893856845",
      "operationId": "BE46235022516136#EUR#75#0241##17",
      "executionDate": "20190614",
      "amount": "17,21",
      "currency": "EUR",
      "description1": "COSTAGOMESXYZ CM-\\r\\nBILLIESXYZ METZELLERXYZ",
      "description2": "1030  KONTZENXYZ\\r\\nBE44 0688 9385 6845  BIC GKCCBEBB\\r\\nREFERTE OPDRACHTGEVER :\\r\\n21160192\\r\\nMEDEDELING :\\r\\n1930676309 - KWARTAAL UITBETALING REM\\r\\nGELDEN CM-MEDIKO PLAN - DEBRUYNE - AN",
      "valueDate": "20190614",
      "detailPresent": false
    }, {
      "movementText": "EUROPESE OVERSCHRIJVING VAN              ",
      "sequenceNb": "0240",
      "pending": false,
      "period": "PREVIOUS",
      "annexes": [],
      "otherParty": "BE44068893856845",
      "operationId": "BE46235022516136#EUR#75#0240##18",
      "executionDate": "20190614",
      "amount": "44,20",
      "currency": "EUR",
      "description1": "COSTAGOMESXYZ CM-\\r\\nBILLIESXYZ METZELLERXYZ",
      "description2": "1030  KONTZENXYZ\\r\\nBE44 0688 9385 6845  BIC GKCCBEBB\\r\\nREFERTE OPDRACHTGEVER :\\r\\n21168417\\r\\nMEDEDELING :\\r\\n1930616174 - KWARTAAL UITBETALING REM\\r\\nGELDEN CM-MEDIKO PLAN - VANSTRAELEN -",
      "valueDate": "20190614",
      "detailPresent": false
    }, {
      "movementText": "BETALING AAN BANK CARD COMPANY           ",
      "sequenceNb": "0239",
      "pending": false,
      "period": "PREVIOUS",
      "annexes": [],
      "otherParty": "BETALING AAN BANK CARD COMPANY  ",
      "operationId": "BE46235022516136#EUR#75#0239##19",
      "executionDate": "20190613",
      "amount": "-564,00",
      "currency": "EUR",
      "description1": "INTERNE REKENING MASTERCARD: 18260329\\r\\nUITGAVENSTAAT NUMMER 155",
      "description2": "VALUTADATUM : 13/06/2019",
      "valueDate": "20190613",
      "detailPresent": false
    }, {
      "movementText": "BETALING MET BANKKAART                   ",
      "sequenceNb": "0238",
      "pending": false,
      "period": "PREVIOUS",
      "annexes": [],
      "otherParty": "BETALING MET BANKKAART          ",
      "operationId": "BE46235022516136#EUR#75#0238##20",
      "executionDate": "20190612",
      "amount": "-5,95",
      "currency": "EUR",
      "description1": "MET KAART 6703 04XX XXXX X913 4\\r\\nCCV QUETIN HASSELT",
      "description2": "11/06/2019\\r\\nVALUTADATUM : 11/06/2019",
      "valueDate": "20190611",
      "detailPresent": false
    }, {
      "movementText": "BETALING AAN BANK CARD COMPANY           ",
      "sequenceNb": "0237",
      "pending": false,
      "period": "PREVIOUS",
      "annexes": [],
      "otherParty": "BETALING AAN BANK CARD COMPANY  ",
      "operationId": "BE46235022516136#EUR#75#0237##21",
      "executionDate": "20190611",
      "amount": "-11,98",
      "currency": "EUR",
      "description1": "INTERNE REKENING VISA : 18510329\\r\\nUITGAVENSTAAT NUMMER 152",
      "description2": "VALUTADATUM : 11/06/2019",
      "valueDate": "20190611",
      "detailPresent": false
    }, {
      "movementText": "BETALING MET BANKKAART                   ",
      "sequenceNb": "0236",
      "pending": false,
      "period": "PREVIOUS",
      "annexes": [],
      "otherParty": "BETALING MET BANKKAART          ",
      "operationId": "BE46235022516136#EUR#75#0236##22",
      "executionDate": "20190611",
      "amount": "-139,50",
      "currency": "EUR",
      "description1": "MET KAART 6703 23XX XXXX X250 1\\r\\nCCV T PLEI HASSELT",
      "description2": "09/06/2019\\r\\nVALUTADATUM : 09/06/2019",
      "valueDate": "20190609",
      "detailPresent": false
    }, {
      "movementText": "BETALING MET BANKKAART                   ",
      "sequenceNb": "0235",
      "pending": false,
      "period": "PREVIOUS",
      "annexes": [],
      "otherParty": "BETALING MET BANKKAART          ",
      "operationId": "BE46235022516136#EUR#75#0235##23",
      "executionDate": "20190608",
      "amount": "-60,00",
      "currency": "EUR",
      "description1": "MET KAART 6703 23XX XXXX X250 1\\r\\n4414 DATS 24 HAS  HASSELT",
      "description2": "08/06/2019\\r\\nVALUTADATUM : 08/06/2019",
      "valueDate": "20190608",
      "detailPresent": false
    }, {
      "movementText": "BETALING MET BANKKAART                   ",
      "sequenceNb": "0234",
      "pending": false,
      "period": "PREVIOUS",
      "annexes": [],
      "otherParty": "BETALING MET BANKKAART          ",
      "operationId": "BE46235022516136#EUR#75#0234##24",
      "executionDate": "20190608",
      "amount": "-105,33",
      "currency": "EUR",
      "description1": "MET KAART 6703 23XX XXXX X250 1\\r\\nJANSSEN-CLAES  N  HASSELT",
      "description2": "08/06/2019\\r\\nVALUTADATUM : 08/06/2019",
      "valueDate": "20190608",
      "detailPresent": false
    }, {
      "movementText": "BETALING MET BANKKAART                   ",
      "sequenceNb": "0233",
      "pending": false,
      "period": "PREVIOUS",
      "annexes": [],
      "otherParty": "BETALING MET BANKKAART          ",
      "operationId": "BE46235022516136#EUR#75#0233##25",
      "executionDate": "20190605",
      "amount": "-54,34",
      "currency": "EUR",
      "description1": "MET KAART 6703 23XX XXXX X250 1\\r\\nALDI 31 HASSELT   HASSELT",
      "description2": "05/06/2019\\r\\nVALUTADATUM : 05/06/2019",
      "valueDate": "20190605",
      "detailPresent": false
    }, {
      "movementText": "BETALING MET BANKKAART                   ",
      "sequenceNb": "0232",
      "pending": false,
      "period": "PREVIOUS",
      "annexes": [],
      "otherParty": "BETALING MET BANKKAART          ",
      "operationId": "BE46235022516136#EUR#75#0232##26",
      "executionDate": "20190603",
      "amount": "-13,05",
      "currency": "EUR",
      "description1": "MET KAART 6703 04XX XXXX X913 4\\r\\nSLAGERIJ OOSTERB  HASSELT",
      "description2": "03/06/2019\\r\\nVALUTADATUM : 03/06/2019",
      "valueDate": "20190603",
      "detailPresent": false
    }, {
      "movementText": "BETALING MET BANKKAART                   ",
      "sequenceNb": "0231",
      "pending": false,
      "period": "PREVIOUS",
      "annexes": [],
      "otherParty": "BETALING MET BANKKAART          ",
      "operationId": "BE46235022516136#EUR#75#0231##27",
      "executionDate": "20190603",
      "amount": "-16,60",
      "currency": "EUR",
      "description1": "MET KAART 6703 04XX XXXX X913 4\\r\\nPATISSERIE HASSELT",
      "description2": "29/05/2019\\r\\nVALUTADATUM : 29/05/2019",
      "valueDate": "20190529",
      "detailPresent": false
    }, {
      "movementText": "BETALING MET BANKKAART                   ",
      "sequenceNb": "0230",
      "pending": false,
      "period": "PREVIOUS",
      "annexes": [],
      "otherParty": "BETALING MET BANKKAART          ",
      "operationId": "BE46235022516136#EUR#75#0230##28",
      "executionDate": "20190603",
      "amount": "-18,25",
      "currency": "EUR",
      "description1": "MET KAART 6703 04XX XXXX X913 4\\r\\nCCV QUETIN HASSELT",
      "description2": "01/06/2019\\r\\nVALUTADATUM : 01/06/2019",
      "valueDate": "20190601",
      "detailPresent": false
    }, {
      "movementText": "EUROPESE DOMICILIERING VAN               ",
      "sequenceNb": "0229",
      "pending": false,
      "period": "PREVIOUS",
      "annexes": [],
      "otherParty": "BE82210000088968",
      "operationId": "BE46235022516136#EUR#75#0229##29",
      "executionDate": "20190603",
      "amount": "-73,63",
      "currency": "EUR",
      "description1": "LOOSIXYZ\\r\\nMANDAAT NUMMER :",
      "description2": "B009688156\\r\\nREFERTE :\\r\\n2003280001\\r\\nMEDEDELING :\\r\\n006938062021\\r\\nVALUTADATUM : 03/06/2019",
      "valueDate": "20190603",
      "detailPresent": false
    }, {
      "movementText": "GELDOPNAME AAN ONZE AUTOMATEN            ",
      "sequenceNb": "0228",
      "pending": false,
      "period": "PREVIOUS",
      "annexes": [],
      "otherParty": "GELDOPNAME AAN ONZE AUTOMATEN   ",
      "operationId": "BE46235022516136#EUR#75#0228##30",
      "executionDate": "20190603",
      "amount": "-500,00",
      "currency": "EUR",
      "description1": "MET KAART 6703 04XX XXXX X913 4\\r\\nHASSELT-CENTRUM   HASSELT",
      "description2": "03/06/2019\\r\\nVALUTADATUM : 03/06/2019",
      "valueDate": "20190603",
      "detailPresent": false
    }, {
      "movementText": "BETALING MET BANKKAART                   ",
      "sequenceNb": "0227",
      "pending": false,
      "period": "PREVIOUS",
      "annexes": [],
      "otherParty": "BETALING MET BANKKAART          ",
      "operationId": "BE46235022516136#EUR#75#0227##31",
      "executionDate": "20190601",
      "amount": "-15,98",
      "currency": "EUR",
      "description1": "MET KAART 6703 04XX XXXX X913 4\\r\\nMAES KOFFIE HASS  HASSELT",
      "description2": "01/06/2019\\r\\nVALUTADATUM : 01/06/2019",
      "valueDate": "20190601",
      "detailPresent": false
    }, {
      "movementText": "TERUGBETALING WOONKREDIET                ",
      "sequenceNb": "0226",
      "pending": false,
      "period": "PREVIOUS",
      "annexes": [],
      "otherParty": "TERUGBETALING WOONKREDIET       ",
      "operationId": "BE46235022516136#EUR#75#0226##32",
      "executionDate": "20190601",
      "amount": "-436,80",
      "currency": "EUR",
      "description1": "009-7829087-28\\r\\nVALUTADATUM : 01/06/2019",
      "description2": "",
      "valueDate": "20190601",
      "detailPresent": false
    }, {
      "movementText": "BETALING MET BANKKAART                   ",
      "sequenceNb": "0225",
      "pending": false,
      "period": "PREVIOUS",
      "annexes": [],
      "otherParty": "BETALING MET BANKKAART          ",
      "operationId": "BE46235022516136#EUR#75#0225##33",
      "executionDate": "20190530",
      "amount": "-20,16",
      "currency": "EUR",
      "description1": "MET KAART 6703 04XX XXXX X913 4\\r\\nSPAR EXPRESS SCH  HASSELT",
      "description2": "30/05/2019\\r\\nVALUTADATUM : 30/05/2019",
      "valueDate": "20190530",
      "detailPresent": false
    }, {
      "movementText": "EUROPESE OVERSCHRIJVING VAN              ",
      "sequenceNb": "0224",
      "pending": false,
      "period": "PREVIOUS",
      "annexes": [],
      "otherParty": "BE42784550109254",
      "operationId": "BE46235022516136#EUR#75#0224##34",
      "executionDate": "20190530",
      "amount": "147,33",
      "currency": "EUR",
      "description1": "C.M. STEFFAN\\r\\nGEMMY-GYROSCOOPWEGXYZ 75",
      "description2": "3500  COMAPYZ\\r\\nBE42 7845 5010 9254  BIC GKCCBEBB\\r\\nREFERTE OPDRACHTGEVER :\\r\\n20190528230244000-79707339672805611\\r\\nMEDEDELING :\\r\\n/C/  9 PREST KINE               18/04\\r\\n/19 BASIS TERUGBETAL.  200,34 EUR 411",
      "valueDate": "20190530",
      "detailPresent": false
    }, {
      "movementText": "BETALING MET BANKKAART                   ",
      "sequenceNb": "0223",
      "pending": false,
      "period": "PREVIOUS",
      "annexes": [],
      "otherParty": "BETALING MET BANKKAART          ",
      "operationId": "BE46235022516136#EUR#75#0223##35",
      "executionDate": "20190529",
      "amount": "-14,90",
      "currency": "EUR",
      "description1": "MET KAART 6703 04XX XXXX X913 4\\r\\nSLAGERIJ OOSTERB  HASSELT",
      "description2": "29/05/2019\\r\\nVALUTADATUM : 29/05/2019",
      "valueDate": "20190529",
      "detailPresent": false
    }, {
      "movementText": "BETALING MET BANKKAART                   ",
      "sequenceNb": "0222",
      "pending": false,
      "period": "PREVIOUS",
      "annexes": [],
      "otherParty": "BETALING MET BANKKAART          ",
      "operationId": "BE46235022516136#EUR#75#0222##36",
      "executionDate": "20190529",
      "amount": "-23,22",
      "currency": "EUR",
      "description1": "MET KAART 6703 04XX XXXX X913 4\\r\\n'T VITAMIENTJE N  HASSELT",
      "description2": "29/05/2019\\r\\nVALUTADATUM : 29/05/2019",
      "valueDate": "20190529",
      "detailPresent": false
    }, {
      "movementText": "EUROPESE DOMICILIERING VAN               ",
      "sequenceNb": "0221",
      "pending": false,
      "period": "PREVIOUS",
      "annexes": [],
      "otherParty": "BE76335055459895",
      "operationId": "BE46235022516136#EUR#75#0221##37",
      "executionDate": "20190528",
      "amount": "-400,00",
      "currency": "EUR",
      "description1": "LAFORYZ\\r\\nMANDAAT NUMMER :",
      "description2": "8100002592564\\r\\nREFERTE :\\r\\n002931896115\\r\\nMEDEDELING :\\r\\nLUMINUS VOORSCHOT 5525711686\\r\\nVALUTADATUM : 28/05/2019",
      "valueDate": "20190528",
      "detailPresent": false
    }, {
      "movementText": "BETALING MET BANKKAART                   ",
      "sequenceNb": "0220",
      "pending": false,
      "period": "PREVIOUS",
      "annexes": [],
      "otherParty": "BETALING MET BANKKAART          ",
      "operationId": "BE46235022516136#EUR#75#0220##38",
      "executionDate": "20190527",
      "amount": "-13,20",
      "currency": "EUR",
      "description1": "MET KAART 6703 04XX XXXX X913 4\\r\\nSLAGERIJ OOSTERB  HASSELT",
      "description2": "27/05/2019\\r\\nVALUTADATUM : 27/05/2019",
      "valueDate": "20190527",
      "detailPresent": false
    }, {
      "movementText": "BETALING MET BANKKAART                   ",
      "sequenceNb": "0219",
      "pending": false,
      "period": "PREVIOUS",
      "annexes": [],
      "otherParty": "BETALING MET BANKKAART          ",
      "operationId": "BE46235022516136#EUR#75#0219##39",
      "executionDate": "20190527",
      "amount": "-13,32",
      "currency": "EUR",
      "description1": "MET KAART 6703 04XX XXXX X913 4\\r\\n'T VITAMIENTJE N  HASSELT",
      "description2": "27/05/2019\\r\\nVALUTADATUM : 27/05/2019",
      "valueDate": "20190527",
      "detailPresent": false
    }, {
      "movementText": "BETALING MET BANKKAART                   ",
      "sequenceNb": "0218",
      "pending": false,
      "period": "PREVIOUS",
      "annexes": [],
      "otherParty": "BETALING MET BANKKAART          ",
      "operationId": "BE46235022516136#EUR#75#0218##40",
      "executionDate": "20190527",
      "amount": "-20,50",
      "currency": "EUR",
      "description1": "MET KAART 6703 04XX XXXX X913 4\\r\\nPATISSERIE HASSELT",
      "description2": "24/05/2019\\r\\nVALUTADATUM : 24/05/2019",
      "valueDate": "20190524",
      "detailPresent": false
    }, {
      "movementText": "BETALING MET BANKKAART                   ",
      "sequenceNb": "0217",
      "pending": false,
      "period": "PREVIOUS",
      "annexes": [],
      "otherParty": "BETALING MET BANKKAART          ",
      "operationId": "BE46235022516136#EUR#75#0217##41",
      "executionDate": "20190527",
      "amount": "-490,00",
      "currency": "EUR",
      "description1": "MET KAART 6703 23XX XXXX X250 1\\r\\nDEPOOTER BVBA     HASSELT",
      "description2": "27/05/2019\\r\\nVALUTADATUM : 27/05/2019",
      "valueDate": "20190527",
      "detailPresent": false
    }, {
      "movementText": "EUROPESE OVERSCHRIJVING NAAR             ",
      "sequenceNb": "0216",
      "pending": false,
      "period": "PREVIOUS",
      "annexes": [],
      "otherParty": "BE66001589659743",
      "operationId": "BE46235022516136#EUR#75#0216##42",
      "executionDate": "20190524",
      "amount": "-39,16",
      "currency": "EUR",
      "description1": "MAHSZ NV\\r\\nBE66001589659743",
      "description2": "BIC GEBABEBB    VIA WEB BANKING\\r\\nMEDEDELING :\\r\\nREFERENTIE 1032-109873\\r\\nVALUTADATUM : 24/05/2019",
      "valueDate": "20190524",
      "detailPresent": false
    }, {
      "movementText": "BETALING MET BANKKAART                   ",
      "sequenceNb": "0215",
      "pending": false,
      "period": "PREVIOUS",
      "annexes": [],
      "otherParty": "BETALING MET BANKKAART          ",
      "operationId": "BE46235022516136#EUR#75#0215##43",
      "executionDate": "20190524",
      "amount": "-49,25",
      "currency": "EUR",
      "description1": "MET KAART 6703 04XX XXXX X913 4\\r\\nCCV ALCIME HASSELT",
      "description2": "23/05/2019\\r\\nVALUTADATUM : 23/05/2019",
      "valueDate": "20190523",
      "detailPresent": false
    }, {
      "movementText": "BETALING MET BANKKAART                   ",
      "sequenceNb": "0214",
      "pending": false,
      "period": "PREVIOUS",
      "annexes": [],
      "otherParty": "BETALING MET BANKKAART          ",
      "operationId": "BE46235022516136#EUR#75#0214##44",
      "executionDate": "20190524",
      "amount": "-107,07",
      "currency": "EUR",
      "description1": "MET KAART 6703 23XX XXXX X250 1\\r\\nJANSSEN-CLAES  N  HASSELT",
      "description2": "24/05/2019\\r\\nVALUTADATUM : 24/05/2019",
      "valueDate": "20190524",
      "detailPresent": false
    }, {
      "movementText": "EUROPESE OVERSCHRIJVING NAAR             ",
      "sequenceNb": "0213",
      "pending": false,
      "period": "PREVIOUS",
      "annexes": [],
      "otherParty": "BE42734046370554",
      "operationId": "BE46235022516136#EUR#75#0213##45",
      "executionDate": "20190524",
      "amount": "-200,34",
      "currency": "EUR",
      "description1": "BVBA OBJATYZ\\r\\nBE42734046370554",
      "description2": "BIC KREDBEBB    VIA WEB BANKING\\r\\nMEDEDELING :\\r\\nMEDEDELING 24644137\\r\\nVALUTADATUM : 24/05/2019",
      "valueDate": "20190524",
      "detailPresent": false
    }, {
      "movementText": "EUROPESE OVERSCHRIJVING NAAR             ",
      "sequenceNb": "0212",
      "pending": false,
      "period": "PREVIOUS",
      "annexes": [],
      "otherParty": "BE66001589659743",
      "operationId": "BE46235022516136#EUR#75#0212##46",
      "executionDate": "20190524",
      "amount": "-1.671,10",
      "currency": "EUR",
      "description1": "MAHSZ NV\\r\\nBE66001589659743",
      "description2": "BIC GEBABEBB    VIA WEB BANKING\\r\\nMEDEDELING :\\r\\nREFERENTIE 1032-109873\\r\\nVALUTADATUM : 24/05/2019",
      "valueDate": "20190524",
      "detailPresent": false
    }, {
      "movementText": "GELDOPNAME AAN ONZE AUTOMATEN            ",
      "sequenceNb": "0211",
      "pending": false,
      "period": "PREVIOUS",
      "annexes": [],
      "otherParty": "GELDOPNAME AAN ONZE AUTOMATEN   ",
      "operationId": "BE46235022516136#EUR#75#0211##47",
      "executionDate": "20190523",
      "amount": "-100,00",
      "currency": "EUR",
      "description1": "MET KAART 6703 04XX XXXX X913 4\\r\\nHASSELT-CENTRUM   HASSELT",
      "description2": "23/05/2019\\r\\nVALUTADATUM : 23/05/2019",
      "valueDate": "20190523",
      "detailPresent": false
    }, {
      "movementText": "EUROPESE OVERSCHRIJVING VAN              ",
      "sequenceNb": "0210",
      "pending": false,
      "period": "PREVIOUS",
      "annexes": [],
      "otherParty": "BE44001130665645",
      "operationId": "BE46235022516136#EUR#75#0210##48",
      "executionDate": "20190523",
      "amount": "1.511,17",
      "currency": "EUR",
      "description1": "F.P.D.\\r\\nBE44 0011 3066 5645  BIC GEBABEBB",
      "description2": "REFERTE OPDRACHTGEVER :\\r\\n41110813974 05/2019 00000230966936\\r\\nMEDEDELING :\\r\\n/B/ PENSIOEN 05/2019               NI\\r\\nSS:41110813974 - PID:00230966936 ZIV:\\r\\n55,62                         MEER I\\r\\nNFO:WWW.MYPENSION.BE",
      "valueDate": "20190523",
      "detailPresent": false
    }, {
      "movementText": "BETALING MET BANKKAART                   ",
      "sequenceNb": "0209",
      "pending": false,
      "period": "PREVIOUS",
      "annexes": [],
      "otherParty": "BETALING MET BANKKAART          ",
      "operationId": "BE46235022516136#EUR#75#0209##49",
      "executionDate": "20190522",
      "amount": "-183,10",
      "currency": "EUR",
      "description1": "MET KAART 6703 23XX XXXX X250 1\\r\\nJANSSEN-CLAES  N  HASSELT",
      "description2": "22/05/2019\\r\\nVALUTADATUM : 22/05/2019",
      "valueDate": "20190522",
      "detailPresent": false
    }, {
      "movementText": "EUROPESE DOMICILIERING VAN               ",
      "sequenceNb": "0208",
      "pending": false,
      "period": "PREVIOUS",
      "annexes": [],
      "otherParty": "BE84091010925259",
      "operationId": "BE46235022516136#EUR#75#0208##50",
      "executionDate": "20190522",
      "amount": "-194,14",
      "currency": "EUR",
      "description1": "DE BUROFABXYZ\\r\\nMANDAAT NUMMER :",
      "description2": "MAND15006197\\r\\nREFERTE :\\r\\n986497921361\\r\\nMEDEDELING :\\r\\nFAK192015775\\r\\nVALUTADATUM : 22/05/2019",
      "valueDate": "20190522",
      "detailPresent": false
    }]
  },
  "businessMessageBulk": {
    "messages": [],
    "pewCode": null,
    "globalIndicator": null,
    "text": null
  }
}